pylocker/Locker.py
pylocker/ServerLocker.py
pylocker/__init__.py
pylocker/__pkginfo__.py
pylocker-3.1.0.dist-info/LICENSE.txt
pylocker-3.1.0.dist-info/METADATA
pylocker-3.1.0.dist-info/WHEEL
pylocker-3.1.0.dist-info/top_level.txt
pylocker-3.1.0.dist-info/RECORD
